neochain/__init__.py
neochain/_operations.py
neochain/_release_info.py
neochain/nc_community_handler.py
neochain/nc_graph_handler.py
neochain-1.1.dist-info/METADATA
neochain-1.1.dist-info/RECORD
neochain-1.1.dist-info/WHEEL
neochain-1.1.dist-info/top_level.txt
