Metadata-Version: 2.1
Name: neochain
Version: 1.1
Summary: neochain - Network Evolution Observation for Blockchain
Home-page: https://github.com/dharif23/neochain
Author: Dalwar Hossain
Author-email: dalwar.hossain@protonmail.com
Maintainer: Dalwar Hossain
Maintainer-email: dalwar.hossain@protonmail.com
License: MIT
Download-URL: https://github.com/dharif23/neochain
Keywords: Network,Evolution,Community,Blockchain
Platform: Linux
Platform: Mac OSX
Platform: Windows
Platform: Unix
Classifier: Development Status :: 4 - Beta
Classifier: Intended Audience :: Developers
Classifier: Intended Audience :: Science/Research
Classifier: License :: OSI Approved :: MIT License
Classifier: Operating System :: OS Independent
Classifier: Programming Language :: Python :: 2
Classifier: Programming Language :: Python :: 2.7
Classifier: Programming Language :: Python :: 3
Classifier: Programming Language :: Python :: 3.4
Classifier: Programming Language :: Python :: 3.5
Classifier: Programming Language :: Python :: 3.6
Classifier: Programming Language :: Python :: 3.7
Classifier: Topic :: Software Development :: Libraries :: Python Modules
Requires-Dist: pip (>=18.0)
Requires-Dist: numpy (!=1.15.0)
Requires-Dist: pandas (>=0.23.4)
Requires-Dist: networkx (>=2.1)
Requires-Dist: python-louvain (>=0.11)
Requires-Dist: pyrainbowterm (>=1.0)
Requires-Dist: setuptools (>=40.1.0)
Requires-Dist: six (>=1.10.0)
Requires-Dist: wheel (>=0.31.1)
Requires-Dist: python-dateutil (>=2.7.3)
Requires-Dist: pytz (>=2018.5)
Requires-Dist: sphinx (>=1.7.1)
Requires-Dist: recommonmark (>=0.4.0)
Requires-Dist: sphinx-rtd-theme (>=0.4.1)
